kcol_graph_gen/__init__.py
kcol_graph_gen/generator.py
kcol_graph_gen-1.0.0.dist-info/LICENSE
kcol_graph_gen-1.0.0.dist-info/METADATA
kcol_graph_gen-1.0.0.dist-info/WHEEL
kcol_graph_gen-1.0.0.dist-info/top_level.txt
kcol_graph_gen-1.0.0.dist-info/RECORD
