Metadata-Version: 2.1
Name: kcol-graph-gen
Version: 1.0.0
Summary: Generate a k-colarable graph.
Author-email: Deep Raval <deepraval2905@gmail.com>
License: MIT License
Project-URL: repository, https://github.com/imdeep2905/kcol-graph
Project-URL: documentation, https://github.com/imdeep2905/kcol-graph/blob/main/README.md
Keywords: k-colrable,graph-coloring,chromatic number
Classifier: License :: OSI Approved :: MIT License
Classifier: Programming Language :: Python
Classifier: Programming Language :: Python :: 3
Requires-Python: >=3.7
License-File: LICENSE
Provides-Extra: build
Requires-Dist: build ; extra == 'build'
Requires-Dist: twine ; extra == 'build'
Provides-Extra: dev
Requires-Dist: black ; extra == 'dev'
Requires-Dist: pytest ; extra == 'dev'
